browseversa.py
browseversa-1.0.0.dist-info/licenses/LICENSE
browseversa-1.0.0.dist-info/METADATA
browseversa-1.0.0.dist-info/WHEEL
browseversa-1.0.0.dist-info/entry_points.txt
browseversa-1.0.0.dist-info/top_level.txt
browseversa-1.0.0.dist-info/RECORD
