Metadata-Version: 2.4
Name: browseversa
Version: 1.0.0
Summary: A comprehensive tool to detect web browser versions on Windows systems
Author-email: Pandiyaraj Karuppasamy <pandiyarajk@live.com>
Maintainer-email: Pandiyaraj Karuppasamy <pandiyarajk@live.com>
License-Expression: MIT
Project-URL: Homepage, https://github.com/pandiyarajk/browseversa
Project-URL: Documentation, https://github.com/pandiyarajk/browseversa#readme
Project-URL: Repository, https://github.com/pandiyarajk/browseversa
Project-URL: Bug Tracker, https://github.com/pandiyarajk/browseversa/issues
Keywords: browser,version,detection,chrome,firefox,edge,internet-explorer,windows,automation
Classifier: Development Status :: 5 - Production/Stable
Classifier: Intended Audience :: Developers
Classifier: Intended Audience :: System Administrators
Classifier: Operating System :: Microsoft :: Windows
Classifier: Programming Language :: Python :: 3
Classifier: Programming Language :: Python :: 3.6
Classifier: Programming Language :: Python :: 3.7
Classifier: Programming Language :: Python :: 3.8
Classifier: Programming Language :: Python :: 3.9
Classifier: Programming Language :: Python :: 3.10
Classifier: Programming Language :: Python :: 3.11
Classifier: Programming Language :: Python :: 3.12
Classifier: Topic :: Software Development :: Libraries :: Python Modules
Classifier: Topic :: System :: Systems Administration
Classifier: Topic :: Utilities
Classifier: Topic :: Internet :: WWW/HTTP :: Browsers
Requires-Python: >=3.6
License-File: LICENSE
Provides-Extra: dev
Requires-Dist: pytest>=6.0; extra == "dev"
Requires-Dist: pytest-cov>=2.0; extra == "dev"
Requires-Dist: black>=21.0; extra == "dev"
Requires-Dist: flake8>=3.8; extra == "dev"
Requires-Dist: mypy>=0.800; extra == "dev"
Provides-Extra: docs
Requires-Dist: sphinx>=4.0; extra == "docs"
Requires-Dist: sphinx-rtd-theme>=1.0; extra == "docs"
Dynamic: license-file
